Workbook
Name Aging_Bucket: Raw_data!$T$2:$T$481
Name Average_Inventory: Raw_data!$S$2:$S$481
Name Category: Raw_data!$C$2:$C$481
Name Closing_Stock: Raw_data!$H$2:$H$481
Name Cost_Price: Raw_data!$I$2:$I$481
Name Dead_Stock_flag: Raw_data!$P$2:$P$481
Name Inventory_Value: Raw_data!$U$2:$U$481
Name Low_Margin_Risk: Raw_data!$Q$2:$Q$481
Name Month: Raw_data!$E$2:$E$481
Name Opening_Stock: Raw_data!$F$2:$F$481
Name Overstock_Risk: Raw_data!$R$2:$R$481
Name Product_ID: Raw_data!$A$2:$A$481
Name Product_Name: Raw_data!$B$2:$B$481
Name profit: Raw_data!$M$2:$M$481
Name Profit_margin: Raw_data!$N$2:$N$481
Name Region: Raw_data!$D$2:$D$481
Name Revenue: Raw_data!$K$2:$K$481
Name Selling_Price: Raw_data!$J$2:$J$481
Name Slicer_Category1: #N/A
Name Slicer_Month1: #N/A
Name Slicer_Region1: #N/A
Name Slow_moving_flag: Raw_data!$O$2:$O$481
Name Total_cost: Raw_data!$L$2:$L$481
Name Units_Sold: Raw_data!$G$2:$G$481

Sheet Raw_data
A1: Product_ID | B1: Product_Name | C1: Category | D1: Region | E1: Month | F1: Opening_Stock | G1: Units_Sold | H1: Closing_Stock | I1: Cost_Price | J1: Selling_Price | K1: Revenue | L1: Total cost | M1: profit | N1: Profit margin | O1: Slow moving flag | P1: Dead Stock flag | Q1: Low Margin Risk | R1: Overstock Risk | S1: Average_Inventory | T1: Aging Bucket | U1: Inventory_Value | V1: Total Revenue
A2: P001 | B2: Laptop | C2: Electronics | D2: North | E2: 45658 | F2: 29 | G2: 2 | H2: 27 | I2: 40000 | J2: 50000 | K2: =G2*J2 -> 100000 | L2: =G2*I2 -> 80000 | M2: =K2-L2 -> 20000 | N2: =IF(K2=0,0,M2/K2) -> 0.2 | O2: =IF(G2<20,"Slow Moving","Normal") -> Slow Moving | P2: =IF(G2=0,"Dead Stock","") | Q2: =IF(N2<0.1,"Low Margin","") | S2: =(F2+H2)/2 -> 28 | T2: =IF(H2>200,"90+ Days", IF(H2>100,"60-90 Days", IF(H2>50,"30-60 Days","0-30 Days"))) -> 0-30 Days | U2: =H2 * I2 -> 1080000 | V2: =tbl_inventory[[#This Row],[Units_Sold]]*tbl_inventory[[#This Row],[Revenue]] -> 200000
A3: P001 | B3: Laptop | C3: Electronics | D3: North | E3: 45689 | F3: 98 | G3: 42 | H3: 56 | I3: 40000 | J3: 50000 | K3: =G3*J3 -> 2100000 | L3: =G3*I3 -> 1680000 | M3: =K3-L3 -> 420000 | N3: =IF(K3=0,0,M3/K3) -> 0.2 | O3: =IF(G3<20,"Slow Moving","Normal") -> Normal | P3: =IF(G3=0,"Dead Stock","") | Q3: =IF(N3<0.1,"Low Margin","") | S3: =(F3+H3)/2 -> 77 | T3: =IF(H3>200,"90+ Days", IF(H3>100,"60-90 Days", IF(H3>50,"30-60 Days","0-30 Days"))) -> 30-60 Days | U3: =H3 * I3 -> 2240000 | V3: =tbl_inventory[[#This Row],[Units_Sold]]*tbl_inventory[[#This Row],[Revenue]] -> 88200000
A4: P001 | B4: Laptop | C4: Electronics | D4: North | E4: 45717 | F4: 60 | G4: 0 | H4: 60 | I4: 40000 | J4: 50000 | K4: =G4*J4 -> 0 | L4: =G4*I4 -> 0 | M4: =K4-L4 -> 0 | N4: =IF(K4=0,0,M4/K4) -> 0 | O4: =IF(G4<20,"Slow Moving","Normal") -> Slow Moving | P4: =IF(G4=0,"Dead Stock","") -> Dead Stock | Q4: =IF(N4<0.1,"Low Margin","") -> Low Margin | S4: =(F4+H4)/2 -> 60 | T4: =IF(H4>200,"90+ Days", IF(H4>100,"60-90 Days", IF(H4>50,"30-60 Days","0-30 Days"))) -> 30-60 Days | U4: =H4 * I4 -> 2400000 | V4: =tbl_inventory[[#This Row],[Units_Sold]]*tbl_inventory[[#This Row],[Revenue]] -> 0
A5: P001 | B5: Laptop | C5: Electronics | D5: North | E5: 45748 | F5: 83 | G5: 82 | H5: 1 | I5: 40000 | J5: 50000 | K5: =G5*J5 -> 4100000 | L5: =G5*I5 -> 3280000 | M5: =K5-L5 -> 820000 | N5: =IF(K5=0,0,M5/K5) -> 0.2 | O5: =IF(G5<20,"Slow Moving","Normal") -> Normal | P5: =IF(G5=0,"Dead Stock","") | Q5: =IF(N5<0.1,"Low Margin","") | S5: =(F5+H5)/2 -> 42 | T5: =IF(H5>200,"90+ Days", IF(H5>100,"60-90 Days", IF(H5>50,"30-60 Days","0-30 Days"))) -> 0-30 Days | U5: =H5 * I5 -> 40000 | V5: =tbl_inventory[[#This Row],[Units_Sold]]*tbl_inventory[[#This Row],[Revenue]] -> 336200000
A6: P001 | B6: Laptop | C6: Electronics | D6: North | E6: 45778 | F6: 22 | G6: 0 | H6: 22 | I6: 40000 | J6: 50000 | K6: =G6*J6 -> 0 | L6: =G6*I6 -> 0 | M6: =K6-L6 -> 0 | N6: =IF(K6=0,0,M6/K6) -> 0 | O6: =IF(G6<20,"Slow Moving","Normal") -> Slow Moving | P6: =IF(G6=0,"Dead Stock","") -> Dead Stock | Q6: =IF(N6<0.1,"Low Margin","") -> Low Margin | S6: =(F6+H6)/2 -> 22 | T6: =IF(H6>200,"90+ Days", IF(H6>100,"60-90 Days", IF(H6>50,"30-60 Days","0-30 Days"))) -> 0-30 Days | U6: =H6 * I6 -> 880000 | V6: =tbl_inventory[[#This Row],[Units_Sold]]*tbl_inventory[[#This Row],[Revenue]] -> 0
A7: P001 | B7: Laptop | C7: Electronics | D7: North | E7: 45809 | F7: 79 | G7: 6 | H7: 73 | I7: 40000 | J7: 50000 | K7: =G7*J7 -> 300000 | L7: =G7*I7 -> 240000 | M7: =K7-L7 -> 60000 | N7: =IF(K7=0,0,M7/K7) -> 0.2 | O7: =IF(G7<20,"Slow Moving","Normal") -> Slow Moving | P7: =IF(G7=0,"Dead Stock","") | Q7: =IF(N7<0.1,"Low Margin","") | S7: =(F7+H7)/2 -> 76 | T7: =IF(H7>200,"90+ Days", IF(H7>100,"60-90 Days", IF(H7>50,"30-60 Days","0-30 Days"))) -> 30-60 Days | U7: =H7 * I7 -> 2920000 | V7: =tbl_inventory[[#This Row],[Units_Sold]]*tbl_inventory[[#This Row],[Revenue]] -> 1800000
A8: P001 | B8: Laptop | C8: Electronics | D8: South | E8: 45658 | F8: 32 | G8: 8 | H8: 24 | I8: 40000 | J8: 50000 | K8: =G8*J8 -> 400000 | L8: =G8*I8 -> 320000 | M8: =K8-L8 -> 80000 | N8: =IF(K8=0,0,M8/K8) -> 0.2 | O8: =IF(G8<20,"Slow Moving","Normal") -> Slow Moving | P8: =IF(G8=0,"Dead Stock","") | Q8: =IF(N8<0.1,"Low Margin","") | S8: =(F8+H8)/2 -> 28 | T8: =IF(H8>200,"90+ Days", IF(H8>100,"60-90 Days", IF(H8>50,"30-60 Days","0-30 Days"))) -> 0-30 Days | U8: =H8 * I8 -> 960000 | V8: =tbl_inventory[[#This Row],[Units_Sold]]*tbl_inventory[[#This Row],[Revenue]] -> 3200000
A9: P001 | B9: Laptop | C9: Electronics | D9: South | E9: 45689 | F9: 24 | G9: 7 | H9: 17 | I9: 40000 | J9: 50000 | K9: =G9*J9 -> 350000 | L9: =G9*I9 -> 280000 | M9: =K9-L9 -> 70000 | N9: =IF(K9=0,0,M9/K9) -> 0.2 | O9: =IF(G9<20,"Slow Moving","Normal") -> Slow Moving | P9: =IF(G9=0,"Dead Stock","") | Q9: =IF(N9<0.1,"Low Margin","") | S9: =(F9+H9)/2 -> 20.5 | T9: =IF(H9>200,"90+ Days", IF(H9>100,"60-90 Days", IF(H9>50,"30-60 Days","0-30 Days"))) -> 0-30 Days | U9: =H9 * I9 -> 680000 | V9: =tbl_inventory[[#This Row],[Units_Sold]]*tbl_inventory[[#This Row],[Revenue]] -> 2450000
A10: P001 | B10: Laptop | C10: Electronics | D10: South | E10: 45717 | F10: 31 | G10: 21 | H10: 10 | I10: 40000 | J10: 50000 | K10: =G10*J10 -> 1050000 | L10: =G10*I10 -> 840000 | M10: =K10-L10 -> 210000 | N10: =IF(K10=0,0,M10/K10) -> 0.2 | O10: =IF(G10<20,"Slow Moving","Normal") -> Normal | P10: =IF(G10=0,"Dead Stock","") | Q10: =IF(N10<0.1,"Low Margin","") | S10: =(F10+H10)/2 -> 20.5 | T10: =IF(H10>200,"90+ Days", IF(H10>100,"60-90 Days", IF(H10>50,"30-60 Days","0-30 Days"))) -> 0-30 Days | U10: =H10 * I10 -> 400000 | V10: =tbl_inventory[[#This Row],[Units_Sold]]*tbl_inventory[[#This Row],[Revenue]] -> 22050000
A11: P001 | B11: Laptop | C11: Electronics | D11: South | E11: 45748 | F11: 51 | G11: 17 | H11: 34 | I11: 40000 | J11: 50000 | K11: =G11*J11 -> 850000 | L11: =G11*I11 -> 680000 | M11: =K11-L11 -> 170000 | N11: =IF(K11=0,0,M11/K11) -> 0.2 | O11: =IF(G11<20,"Slow Moving","Normal") -> Slow Moving | P11: =IF(G11=0,"Dead Stock","") | Q11: =IF(N11<0.1,"Low Margin","") | S11: =(F11+H11)/2 -> 42.5 | T11: =IF(H11>200,"90+ Days", IF(H11>100,"60-90 Days", IF(H11>50,"30-60 Days","0-30 Days"))) -> 0-30 Days | U11: =H11 * I11 -> 1360000 | V11: =tbl_inventory[[#This Row],[Units_Sold]]*tbl_inventory[[#This Row],[Revenue]] -> 14450000
A12: P001 | B12: Laptop | C12: Electronics | D12: South | E12: 45778 | F12: 36 | G12: 27 | H12: 9 | I12: 40000 | J12: 50000 | K12: =G12*J12 -> 1350000 | L12: =G12*I12 -> 1080000 | M12: =K12-L12 -> 270000 | N12: =IF(K12=0,0,M12/K12) -> 0.2 | O12: =IF(G12<20,"Slow Moving","Normal") -> Normal | P12: =IF(G12=0,"Dead Stock","") | Q12: =IF(N12<0.1,"Low Margin","") | S12: =(F12+H12)/2 -> 22.5 | T12: =IF(H12>200,"90+ Days", IF(H12>100,"60-90 Days", IF(H12>50,"30-60 Days","0-30 Days"))) -> 0-30 Days | U12: =H12 * I12 -> 360000 | V12: =tbl_inventory[[#This Row],[Units_Sold]]*tbl_inventory[[#This Row],[Revenue]] -> 36450000
A13: P001 | B13: Laptop | C13: Electronics | D13: South | E13: 45809 | F13: 53 | G13: 14 | H13: 39 | I13: 40000 | J13: 50000 | K13: =G13*J13 -> 700000 | L13: =G13*I13 -> 560000 | M13: =K13-L13 -> 140000 | N13: =IF(K13=0,0,M13/K13) -> 0.2 | O13: =IF(G13<20,"Slow Moving","Normal") -> Slow Moving | P13: =IF(G13=0,"Dead Stock","") | Q13: =IF(N13<0.1,"Low Margin","") | S13: =(F13+H13)/2 -> 46 | T13: =IF(H13>200,"90+ Days", IF(H13>100,"60-90 Days", IF(H13>50,"30-60 Days","0-30 Days"))) -> 0-30 Days | U13: =H13 * I13 -> 1560000 | V13: =tbl_inventory[[#This Row],[Units_Sold]]*tbl_inventory[[#This Row],[Revenue]] -> 9800000
... A481: P020 | B481: Bag | C481: Accessories | D481: West | E481: 45809 | F481: 181 | G481: 157 | H481: 24 | I481: 1000 | J481: 2500 | K481: =G481*J481 -> 392500 | L481: =G481*I481 -> 157000 | M481: =K481-L481 -> 235500 | N481: =IF(K481=0,0,M481/K481) -> 0.6 | O481: =IF(G481<20,"Slow Moving","Normal") -> Normal | P481: =IF(G481=0,"Dead Stock","") | Q481: =IF(N481<0.1,"Low Margin","") | S481: =(F481+H481)/2 -> 102.5 | T481: =IF(H481>200,"90+ Days", IF(H481>100,"60-90 Days", IF(H481>50,"30-60 Days","0-30 Days"))) -> 0-30 Days | U481: =H481 * I481 -> 24000 | V481: =tbl_inventory[[#This Row],[Units_Sold]]*tbl_inventory[[#This Row],[Revenue]] -> 61622500

Sheet Product_Master
A1: Product_ID | B1: Product_Name | C1: Category | D1: Cost_Price | E1: Selling_Price
A2: P001 | B2: Laptop | C2: Electronics | D2: 40000 | E2: 50000
A3: P002 | B3: Mobile | C3: Electronics | D3: 15000 | E3: 20000
A4: P003 | B4: Tv | C4: Electronics | D4: 30000 | E4: 38000
A5: P004 | B5: Headphones | C5: Electronics | D5: 2000 | E5: 3500
A6: P005 | B6: Sofa | C6: Furniture | D6: 15000 | E6: 22000
A7: P006 | B7: Dining Table | C7: Furniture | D7: 12000 | E7: 18000
A8: P007 | B8: Chair | C8: Furniture | D8: 2000 | E8: 3500
A9: P008 | B9: Bed | C9: Furniture | D9: 20000 | E9: 28000
A10: P009 | B10: Rice Pack | C10: Grocery | D10: 40 | E10: 60
A11: P010 | B11: oil | C11: Grocery | D11: 90 | E11: 120
A12: P011 | B12: Sugar | C12: Grocery | D12: 35 | E12: 55
A13: P012 | B13: Flour | C13: Grocery | D13: 30 | E13: 50
... A21: P020 | B21: Bag | C21: Accessories | D21: 1000 | E21: 2500
A22: P021
A23: P022
A24: P023
A25: P024
A26: P025
A27: P026
A28: P027
A29: P028
A30: P029

Sheet Dashboard_data
A1: Row Labels | B1: Sum of Inventory_Value | C1: Sum of profit | D1: Sum of Revenue | E1: Sum of Cost_Price | F1: Sum of Closing_Stock | G1: Average of Average_Inventory | H1: Count of Product_ID | I1: Count of Slow moving flag | J1: Sum of Total cost
A2: Normal | B2: 42856880 | C2: 29287070 | D2: 93097425 | E2: 1542775 | F2: 32806 | G2: 163.38609 | H2: 338 | I2: 338 | J2: 63810355
A3: Slow Moving | B3: 62395205 | C3: 5986060 | D3: 22518235 | E3: 1881905 | F3: 7404 | G3: 56.34507 | H3: 142 | I3: 142 | J3: 16532175
A4: Grand Total | B4: 105252085 | C4: 35273130 | D4: 115615660 | E4: 3424680 | F4: 40210 | G4: 131.71979 | H4: 480 | I4: 480 | J4: 80342530
B5: =GETPIVOTDATA("Sum of Inventory_Value",$A$1) -> 105252085 | C5: =GETPIVOTDATA("Sum of profit",$A$1) -> 35273130 | D5: =GETPIVOTDATA("Sum of Revenue",$A$1) -> 115615660 | E5: Inventory Turnover Ratio= | F5: =GETPIVOTDATA("Sum of Total cost",$A$1)/GETPIVOTDATA("Sum of Inventory_Value",$A$1) -> 0.76333433 | G5: % Slow Moving= | H5: =GETPIVOTDATA("Count of Slow moving flag",$A$1,"Slow moving flag","Slow Moving")/GETPIVOTDATA("Count of Slow moving flag",$A$1) -> 0.29583333 | I5: Profit margin %= | J5: =GETPIVOTDATA("Sum of profit",$A$1)/GETPIVOTDATA("Sum of Revenue",$A$1) -> 0.30508955
A7: Row Labels | B7: Sum of Closing_Stock | D7: Row Labels | E7: Sum of profit | G7: Row Labels | H7: Sum of Revenue | I7: Sum of profit | K7: Row Labels | L7: Sum of Closing_Stock
A8: Furniture | B8: 1724 | D8: South | E8: 9146470 | G8: 45658 | H8: 19910975 | I8: 6252970 | K8: 0-30 Days | L8: 6059
A9: Electronics | B9: 3261 | D9: West | E9: 8878480 | G9: 45689 | H9: 20834355 | I9: 5876260 | K9: 30-60 Days | L9: 6760
A10: Accessories | B10: 5541 | D10: East | E10: 8624360 | G10: 45717 | H10: 20391845 | I10: 6466570 | K10: 60-90 Days | L10: 7104
A11: Clothing | B11: 7199 | D11: North | E11: 8623820 | G11: 45748 | H11: 20590740 | I11: 6266840 | K11: 90+ Days | L11: 20287
A12: Grocery | B12: 22485 | D12: Grand Total | E12: 35273130 | G12: 45778 | H12: 17420100 | I12: 5223940 | K12: Grand Total | L12: 40210
A13: Grand Total | B13: 40210 | G13: 45809 | H13: 16467645 | I13: 5186550
G14: Grand Total | H14: 115615660 | I14: 35273130
A16: Row Labels | B16: Sum of profit | D16: =GETPIVOTDATA("Sum of profit",$A$1) -> 35273130
A17: Mobile | B17: 2815000
A18: Watch | B18: 2944000
A19: Bed | B19: 3288000
A20: Laptop | B20: 4790000
A21: Tv | B21: 5296000
A22: Grand Total | B22: 19133000 | C22: =19133000/35273130*100 -> 54.242422

Sheet Inventory_Risk_Dashboard
A1: INVENTORY RISK & PERFORMANCE DASHBOARD
A2: Interactive Dashboard | Filter by Region, Category & Month
B3: Total Revenue | E3: Total Profit | H3: Profit margin % | K3: Inventory value | N3: Inventory Turnover | Q3: % Slow moving products
B4: =Dashboard_data!B5 -> 105252085 | E4: =Dashboard_data!C5 -> 35273130 | H4: =Dashboard_data!J5 -> 0.30508955 | K4: =Dashboard_data!B5 -> 105252085 | N4: =Dashboard_data!F5 -> 0.76333433 | Q4: =Dashboard_data!H5 -> 0.29583333
J23: • Top 5 products contribute approximately 50–60% of total revenue, indicating high dependency on limited SKUs. • Electronics category shows highest profitability, driving overall margin performance. • Slow-moving inventory accounts for over 25%, suggesting opportunity for stock optimization. • Inventory turnover of 0.76 indicates slower capital rotation, requiring demand alignment.
